noahs_local_ollama_chat_agent/__init__.py
noahs_local_ollama_chat_agent/agent.py
noahs_local_ollama_chat_agent/basic_web_scraping.py
noahs_local_ollama_chat_agent/local_agent_tools.py
noahs_local_ollama_chat_agent/local_semantic_db.py
noahs_local_ollama_chat_agent/local_sql_db.py
noahs_local_ollama_chat_agent/semantic_text_splitter.py
noahs_local_ollama_chat_agent-0.1.8.dist-info/METADATA
noahs_local_ollama_chat_agent-0.1.8.dist-info/WHEEL
noahs_local_ollama_chat_agent-0.1.8.dist-info/top_level.txt
noahs_local_ollama_chat_agent-0.1.8.dist-info/RECORD
